pyselenscrapr/ScrapingBackend.py
pyselenscrapr/ScrapingBot.py
pyselenscrapr/ScrapingLogic.py
pyselenscrapr/ScrapingStep.py
pyselenscrapr/ScrapingStepGroup.py
pyselenscrapr/ScrapingStepLoop.py
pyselenscrapr/ScrapingStepPagination.py
pyselenscrapr/ValidationError.py
pyselenscrapr/__init__.py
pyselenscrapr-0.0.81.dist-info/LICENSE
pyselenscrapr-0.0.81.dist-info/METADATA
pyselenscrapr-0.0.81.dist-info/WHEEL
pyselenscrapr-0.0.81.dist-info/top_level.txt
pyselenscrapr-0.0.81.dist-info/RECORD
