Metadata-Version: 2.1
Name: pyselenscrapr
Version: 0.0.81
Summary: A web scraping library for selenium and beautifulsoup
Author-email: donnercody <donnercody86@gmail.com>
Requires-Python: >=3.7
License-File: LICENSE
Requires-Dist: requests
Requires-Dist: beautifulsoup4
Requires-Dist: pandas
Requires-Dist: selenium
Requires-Dist: webdriver-manager
Requires-Dist: numpy
Requires-Dist: tqdm
